nbdapi/__init__.py
nbdapi/nbdapi.py
nbdapi-0.0.2.dist-info/LICENSE
nbdapi-0.0.2.dist-info/METADATA
nbdapi-0.0.2.dist-info/WHEEL
nbdapi-0.0.2.dist-info/top_level.txt
nbdapi-0.0.2.dist-info/RECORD
